aioredis_rate_limiter/__init__.py
aioredis_rate_limiter/rate_limiter.py
aioredis_rate_limiter-0.1.0.dist-info/LICENSE
aioredis_rate_limiter-0.1.0.dist-info/METADATA
aioredis_rate_limiter-0.1.0.dist-info/WHEEL
aioredis_rate_limiter-0.1.0.dist-info/RECORD
