Metadata-Version: 2.1
Name: aioredis-rate-limiter
Version: 0.1.0
Summary: Rate limiter implements on Redis
License: MIT
Keywords: aioredis,redis,rate-limiting,distributed,asyncio
Author: DFilyushin
Author-email: Dmitriy.Filyushin@yandex.ru
Requires-Python: >=3.10,<4.0
Classifier: Development Status :: 5 - Production/Stable
Classifier: Environment :: Web Environment
Classifier: Intended Audience :: Developers
Classifier: License :: OSI Approved :: MIT License
Classifier: Operating System :: OS Independent
Classifier: Programming Language :: Python
Classifier: Programming Language :: Python :: 3
Classifier: Programming Language :: Python :: 3.10
Classifier: Programming Language :: Python :: 3.11
Classifier: Topic :: Software Development
Classifier: Topic :: Software Development :: Libraries
Classifier: Topic :: Software Development :: Libraries :: Python Modules
Classifier: Typing :: Typed
Requires-Dist: aioredis (>=2.0.1,<3.0.0)
